{"Korijen": "frcnuti", "podrjetlo": ["\u2192 frk"], "vrstaRijeci": "glagol svr\u0161eni neprijelazni", "izgovor": ["frcnuti"], "gram_obilj": {"vremena": {"prezent": {"jednina": "-em", "mnozina": "-u"}, "imperativ": "-i", "aorist": "-uh", "glagolski prilog prosli": "-uv\u0161i", "glagolski pridjev radni": "-uo/-la/-lo"}}, "definicije": [{"-": "naglo isko\u010diti, izbiti odakle (kao iskra iz vatre)", "primjer": ["Ne\u0161to je frcnulo iz grma."], "special": "Vid. par. frcati", "sinonimi": ["vrcnuti"]}]}