{"Korijen": "frekventirati", "podrjetlo": ["\u2192 frekvencija"], "dodatno": "frekventiranje gl im", "vrstaRijeci": "glagol dvovidni prijelazni", "izgovor": ["frekventirati"], "gram_obilj": {"vremena": {"prezent": {"jednina": "frekventiram", "mnozina": "-aju"}, "imperativ": "frekventiraj", "aorist": "-ah", "imperfekt": "frekventirah", "glagolski prilog sada\u0161nji": "-aju\u0107i", "glagolski prilog prosli": "-av\u0161i", "glagolski pridjev radni": "-ao/-la/-lo", "glagolski pridjev trpni": "frekventiran"}}, "definicije": [{"-": "(\u0161to) prolaziti kojim prostorom, \u010desto posje\u0107ivati koje mjesto", "primjer": ["Kroz pothodnik frekventira dnevno tisu\u0107e ljudi."]}]}